README.txt
setup.cfg
setup.py
rcom/__init__.py
rcom.pas.gapps.egg-info/PKG-INFO
rcom.pas.gapps.egg-info/SOURCES.txt
rcom.pas.gapps.egg-info/dependency_links.txt
rcom.pas.gapps.egg-info/entry_points.txt
rcom.pas.gapps.egg-info/namespace_packages.txt
rcom.pas.gapps.egg-info/not-zip-safe
rcom.pas.gapps.egg-info/paster_plugins.txt
rcom.pas.gapps.egg-info/requires.txt
rcom.pas.gapps.egg-info/top_level.txt
rcom/pas/__init__.py
rcom/pas/gapps/__init__.py
rcom/pas/gapps/config.py
rcom/pas/gapps/install.py
rcom/pas/gapps/interface.py
rcom/pas/gapps/plugin.py
rcom/pas/gapps/browser/__init__.py
rcom/pas/gapps/plugins/__init__.py
rcom/pas/gapps/tests/__init__.py
rcom/pas/gapps/tests/base.py
rcom/pas/gapps/tests/test_gapps_pas.py