Metadata-Version: 1.0
Name: rcom.pas.gapps
Version: 1.0dev-r598
Summary: PAS plugin for GoogleApps domains.
Home-page: http://www.rcom.com.ar/
Author: Rcom
Author-email: info@rcom.com.ar
License: GPL
Platform: UNKNOWN
Classifier: Framework :: Plone
Classifier: Intended Audience :: Developers
Classifier: Topic :: Software Development :: Libraries :: Python Modules
Classifier: License :: OSI Approved :: GNU General Public License (GPL)
